hf_dataset_structurer/DatasetStructure.py
hf_dataset_structurer/__init__.py
hf_dataset_structurer/example.py
hf_dataset_structurer-0.0.6.dist-info/LICENSE
hf_dataset_structurer-0.0.6.dist-info/METADATA
hf_dataset_structurer-0.0.6.dist-info/WHEEL
hf_dataset_structurer-0.0.6.dist-info/top_level.txt
hf_dataset_structurer-0.0.6.dist-info/RECORD
