Metadata-Version: 2.1
Name: hf_dataset_structurer
Version: 0.0.6
Summary: A package to structure datasets in the Hugging Face Hub
Home-page: https://github.com/arubenruben/hf_dataset_structurer
Author: Rúben Almeida
Author-email: ruben.f.almeida@inesctec.pt
License: MIT
License-File: LICENSE
Requires-Dist: datasets
Requires-Dist: Jinja2
Requires-Dist: huggingface-hub
